setup.py
pyStrich.egg-info/PKG-INFO
pyStrich.egg-info/SOURCES.txt
pyStrich.egg-info/dependency_links.txt
pyStrich.egg-info/requires.txt
pyStrich.egg-info/top_level.txt
pystrich/__init__.py
pystrich/code128/__init__.py
pystrich/code128/encoding.py
pystrich/code128/generate_test.py
pystrich/code128/renderer.py
pystrich/code128/test_code128.py
pystrich/code128/textencoder.py
pystrich/datamatrix/__init__.py
pystrich/datamatrix/placement.py
pystrich/datamatrix/reedsolomon.py
pystrich/datamatrix/renderer.py
pystrich/datamatrix/test_datamatrix.py
pystrich/datamatrix/textencoder.py
pystrich/ean13/__init__.py
pystrich/ean13/encoding.py
pystrich/ean13/generate_test.py
pystrich/ean13/renderer.py
pystrich/ean13/test_ean13.py
pystrich/fonts/__init__.py
pystrich/fonts/cour.pbm
pystrich/fonts/cour.pil
pystrich/fonts/courR08.pbm
pystrich/fonts/courR08.pil
pystrich/fonts/courR10.pbm
pystrich/fonts/courR10.pil
pystrich/fonts/courR12.pbm
pystrich/fonts/courR12.pil
pystrich/fonts/courR14.pbm
pystrich/fonts/courR14.pil
pystrich/fonts/courR18.pbm
pystrich/fonts/courR18.pil
pystrich/fonts/courR24.pbm
pystrich/fonts/courR24.pil
pystrich/qrcode/__init__.py
pystrich/qrcode/isodata.py
pystrich/qrcode/renderer.py
pystrich/qrcode/test_qrcode.py
pystrich/qrcode/textencoder.py
pystrich/qrcode/qrcode_data/qrv10_0.dat
pystrich/qrcode/qrcode_data/qrv10_1.dat
pystrich/qrcode/qrcode_data/qrv10_2.dat
pystrich/qrcode/qrcode_data/qrv10_3.dat
pystrich/qrcode/qrcode_data/qrv11_0.dat
pystrich/qrcode/qrcode_data/qrv11_1.dat
pystrich/qrcode/qrcode_data/qrv11_2.dat
pystrich/qrcode/qrcode_data/qrv11_3.dat
pystrich/qrcode/qrcode_data/qrv12_0.dat
pystrich/qrcode/qrcode_data/qrv12_1.dat
pystrich/qrcode/qrcode_data/qrv12_2.dat
pystrich/qrcode/qrcode_data/qrv12_3.dat
pystrich/qrcode/qrcode_data/qrv13_0.dat
pystrich/qrcode/qrcode_data/qrv13_1.dat
pystrich/qrcode/qrcode_data/qrv13_2.dat
pystrich/qrcode/qrcode_data/qrv13_3.dat
pystrich/qrcode/qrcode_data/qrv14_0.dat
pystrich/qrcode/qrcode_data/qrv14_1.dat
pystrich/qrcode/qrcode_data/qrv14_2.dat
pystrich/qrcode/qrcode_data/qrv14_3.dat
pystrich/qrcode/qrcode_data/qrv15_0.dat
pystrich/qrcode/qrcode_data/qrv15_1.dat
